vastdb/__init__.py
vastdb/_adbc.py
vastdb/_ibis_support.py
vastdb/_internal.py
vastdb/_table_interface.py
vastdb/bucket.py
vastdb/config.py
vastdb/conftest.py
vastdb/errors.py
vastdb/features.py
vastdb/schema.py
vastdb/session.py
vastdb/table.py
vastdb/table_metadata.py
vastdb/transaction.py
vastdb/util.py
vastdb/bench/__init__.py
vastdb/bench/test_perf.py
vastdb/bench/test_sample.py
vastdb/bench/perf_bench/__init__.py
vastdb/bench/perf_bench/cli.py
vastdb/bench/perf_bench/run.py
vastdb/bench/perf_bench/bench_repo/__init__.py
vastdb/bench/perf_bench/bench_repo/mega_combo.py
vastdb/bench/perf_bench/common/__init__.py
vastdb/bench/perf_bench/common/constants.py
vastdb/bench/perf_bench/common/log_utils.py
vastdb/bench/perf_bench/common/types.py
vastdb/bench/perf_bench/common/utils.py
vastdb/bench/perf_bench/dataset/__init__.py
vastdb/bench/perf_bench/dataset/generate_secmaster.py
vastdb/bench/perf_bench/dataset/generate_stocks_dataset.py
vastdb/bench/perf_bench/dataset/schemas.py
vastdb/bench/perf_bench/dataset/secmaster.py
vastdb/bench/perf_bench/orchestrate/__init__.py
vastdb/bench/perf_bench/orchestrate/bench_spec.py
vastdb/bench/perf_bench/orchestrate/results_helpers.py
vastdb/bench/perf_bench/orchestrate/scenario.py
vastdb/bench/perf_bench/orchestrate/scenario_generator.py
vastdb/bench/perf_bench/query/__init__.py
vastdb/bench/perf_bench/query/arrow_common.py
vastdb/bench/perf_bench/query/query.py
vastdb/bench/perf_bench/query/query_pyarrow.py
vastdb/bench/perf_bench/query/query_vastdb.py
vastdb/tests/__init__.py
vastdb/tests/metrics.py
vastdb/tests/test_adbc_integration.py
vastdb/tests/test_duckdb.py
vastdb/tests/test_fixed_list.py
vastdb/tests/test_imports.py
vastdb/tests/test_nested.py
vastdb/tests/test_projections.py
vastdb/tests/test_sanity.py
vastdb/tests/test_schemas.py
vastdb/tests/test_table_in_tx.py
vastdb/tests/test_tables.py
vastdb/tests/test_util.py
vastdb/tests/test_vector_index.py
vastdb/tests/test_vector_search.py
vastdb/tests/util.py
vastdb-2.0.7.dist-info/licenses/LICENSE
vastdb-2.0.7.dist-info/METADATA
vastdb-2.0.7.dist-info/WHEEL
vastdb-2.0.7.dist-info/top_level.txt
vastdb-2.0.7.dist-info/RECORD
